hypothetical/__init__.py
hypothetical/_lib.py
hypothetical/aov.py
hypothetical/contingency.py
hypothetical/critical.py
hypothetical/descriptive.py
hypothetical/fa.py
hypothetical/gof.py
hypothetical/goodness_fit.py
hypothetical/hypothesis.py
hypothetical/multicomp.py
hypothetical/nonparametric.py
hypothetical/normality.py
hypothetical/posthoc.py
hypothetical/summary.py
hypothetical-0.3.0.dist-info/LICENSE.txt
hypothetical-0.3.0.dist-info/METADATA
hypothetical-0.3.0.dist-info/WHEEL
hypothetical-0.3.0.dist-info/top_level.txt
hypothetical-0.3.0.dist-info/RECORD
