Metadata-Version: 2.1
Name: hypothetical
Version: 0.3.0
Summary: Hypothesis testing and other testing methods
Home-page: UNKNOWN
Author: Aaron Schlegel
Author-email: aaron@aaronschlegel.me
License: UNKNOWN
Platform: UNKNOWN
Classifier: Environment :: Console
Classifier: Intended Audience :: End Users/Desktop
Classifier: Intended Audience :: Developers
Classifier: Intended Audience :: Science/Research
Classifier: Operating System :: OS Independent
Classifier: Programming Language :: Python
Classifier: Programming Language :: Python :: 3
Classifier: Programming Language :: Python :: 3.5
Classifier: Programming Language :: Python :: 3.6
Classifier: Programming Language :: Python :: 3.7
Classifier: Topic :: Scientific/Engineering :: Mathematics
Classifier: Topic :: Software Development :: Libraries :: Python Modules
Requires-Dist: numpy (>=1.13.0)
Requires-Dist: numpy-indexed (>=0.3.5)
Requires-Dist: pandas (>=0.22.0)
Requires-Dist: scipy (>=1.1.0)
